ai_utils/__init__.py
ai_utils/graphics/__init__.py
ai_utils/metrics/__init__.py
ai_utils-1.1.3.dist-info/METADATA
ai_utils-1.1.3.dist-info/WHEEL
ai_utils-1.1.3.dist-info/top_level.txt
ai_utils-1.1.3.dist-info/RECORD
